Metadata-Version: 1.1
Name: metzoo-python-parser-xls-consumo-puan-plugin
Version: 0.0.1
Summary: Python Puan energy report XLS parser Pluigin for Metzoo
Home-page: https://bitbucket.org/edrans/metzoo-python-parser-xls-consumo-puan-plugin
Author: Edrans
Author-email: info@edrans.com
License: MIT
Keywords: metzoo monitoring metric parser
Platform: UNKNOWN
Classifier: Development Status :: 4 - Beta
Classifier: License :: OSI Approved :: MIT License
Classifier: Programming Language :: Python :: 2.7
